AUTHORS
LICENSE
MANIFEST.in
README.rst
setup.py
demo_project/requirements.txt
demo_project/demo_project/__init__.py
demo_project/demo_project/settings.py
demo_project/demo_project/urls.py
demo_project/demo_project/wsgi.py
demo_project/fixtures/initial_data.json
demo_project/media/upload/.DS_Store
demo_project/media/upload/Building.jpg
demo_project/media/upload/Coconut_Trees.jpg
demo_project/media/upload/River.jpg
demo_project/media/upload/Sunset.jpg
demo_project/media/upload/license.txt
demo_project/templates/media_tree/base.html
django_media_tree.egg-info/PKG-INFO
django_media_tree.egg-info/SOURCES.txt
django_media_tree.egg-info/dependency_links.txt
django_media_tree.egg-info/top_level.txt
docs/.gitignore
docs/admin.rst
docs/bundled_extensions.rst
docs/bundled_plugins.rst
docs/conf.py
docs/configuration.rst
docs/custom_plugins.rst
docs/extending.rst
docs/fields.rst
docs/index.rst
docs/installation.rst
docs/management.rst
docs/models.rst
docs/templates.rst
docs/utils.rst
docs/views.rst
docs/_static/admin-screenshot.png
docs/dummy/__init__.py
docs/dummy/media_backends.py
docs/dummy/settings.py
media_tree/__init__.py
media_tree/fields.py
media_tree/forms.py
media_tree/media_types.py
media_tree/models.py
media_tree/settings.py
media_tree/tests.py
media_tree/widgets.py
media_tree/admin/__init__.py
media_tree/admin/change_list.py
media_tree/admin/filenode_admin.py
media_tree/admin/utils.py
media_tree/admin/actions/__init__.py
media_tree/admin/actions/core_actions.py
media_tree/admin/actions/forms.py
media_tree/admin/actions/maintenance_actions.py
media_tree/admin/actions/utils.py
media_tree/contrib/.DS_Store
media_tree/contrib/__init__.py
media_tree/contrib/cms_plugins/__init__.py
media_tree/contrib/cms_plugins/forms.py
media_tree/contrib/cms_plugins/helpers.py
media_tree/contrib/cms_plugins/settings.py
media_tree/contrib/cms_plugins/media_tree_gallery/__init__.py
media_tree/contrib/cms_plugins/media_tree_gallery/cms_plugins.py
media_tree/contrib/cms_plugins/media_tree_gallery/models.py
media_tree/contrib/cms_plugins/media_tree_gallery/templates/cms/plugins/media_tree_gallery.html
