Metadata-Version: 1.1
Name: django-media-tree
Version: 0.8.0
Summary: Django Media Tree is a Django app for managing your website's media files in a folder tree, and using them in your own applications.
Home-page: http://github.com/samluescher/django-media-tree
Author: Samuel Luescher
Author-email: sam at luescher dot org
License: BSD
Platform: UNKNOWN
Classifier: Development Status :: 4 - Beta
Classifier: Framework :: Django
Classifier: Intended Audience :: Developers
Classifier: License :: OSI Approved :: BSD License
Classifier: Operating System :: OS Independent
Classifier: Programming Language :: Python
Classifier: Topic :: Internet :: WWW/HTTP
